Workbook

Sheet Cover
B3: AON PLC – DISCOUNTED CASH FLOW VALUATION
B4: Corporate Finance | Placement Analyst Project
B6: Company | C6: Aon plc (NYSE: AON)
B7: Sector | C7: Professional Services / Insurance Advisory
B8: Model Date | C8: 46113
B9: Currency | C9: USD (millions)
B10: Prepared by | C10: Arun Drubhra
B11: Source | C11: Aon 2025 Annual Report / 10-K
B13: SHEET INDEX
B14: Assumptions | C14: Key model inputs and scenario drivers
B15: Income Statement | C15: Historical and projected P&L
B16: FCF Build | C16: Free cash flow bridge
B17: DCF Valuation | C17: WACC, terminal value, implied price
B18: Sensitivity | C18: Price sensitivity to WACC and growth
B19: Trading Comps | C19: Peer EV/EBITDA and P/E multiples, implied prices
B20: Football Field | C20: Visual summary of valuation range across all methods
B21: Blue text | C21: Hardcoded inputs (change for scenarios)
B22: Black text | C22: Formulas / calculations
B23: Green text | C23: Links from other sheets
B24: Yellow fill | C24: Key assumptions requiring review

Sheet Assumptions
B2: MODEL ASSUMPTIONS – Aon plc
B4: Revenue Assumptions
B5: Assumption | C5: Base Case | D5: Note
B6: FY2025A Revenue (actual, $mm) | C6: 17111 | D6: Aon 2025 10-K (9% growth on $15,698mm)
B7: FY2026E Revenue Growth | C7: 0.055 | D7: Consensus estimate ~6%
B8: FY2027E Revenue Growth | C8: 0.052 | D8: Modest deceleration
B9: FY2028E Revenue Growth | C9: 0.05
B10: FY2029E Revenue Growth | C10: 0.048
B11: FY2030E Revenue Growth | C11: 0.045
B14: Margin & Cost Assumptions
B15: Assumption | C15: Base Case | D15: Note
B16: EBITDA Margin (FY2025A) | C16: 0.324 | D16: Aon 2025 Annual Report (adj. op. margin 32.4%)
B17: EBITDA Margin (FY2026-30E) | C17: 0.33 | D17: Slight expansion; management guiding margin growth
B18: D&A as % of Revenue | C18: 0.028 | D18: ~$440mm on $15.7bn rev
B19: Capex as % of Revenue | C19: 0.018 | D19: Asset-light model
B20: Change in Working Capital (% Rev) | C20: -0.005 | D20: Small WC outflow
B21: Effective Tax Rate | C21: 0.185 | D21: Aon guided ~18-19%
B24: WACC Assumptions
B25: Assumption | C25: Value | D25: Note
B26: Risk-Free Rate (10yr UST) | C26: 0.043 | D26: ~4.3% as at June 2025
B27: Equity Risk Premium | C27: 0.055 | D27: Damodaran US ERP
B28: Beta (5yr monthly, vs S&P 500) | C28: 1.05 | D28: Bloomberg estimate
B29: Cost of Equity | C29: =C26+C28*C27 -> 0.10075 | D29: RFR + Beta x ERP
B30: Pre-Tax Cost of Debt | C30: 0.052 | D30: Aon senior notes avg yield
B31: Tax Rate (for WACC) | C31: 0.19 | D31: Matches income statement
B32: After-Tax Cost of Debt | C32: =C30*(1-C31) -> 0.04212 | D32: Kd x (1-t)
B33: Debt / (Debt + Equity) | C33: 0.38 | D33: Aon capital structure
B34: Equity / (Debt + Equity) | C34: 0.62
B35: WACC | C35: =C29*C34+C32*C33 -> 0.0784706 | D35: Ke x We + Kd(1-t) x Wd
B36: Terminal Growth Rate | C36: 0.025 | D36: ~nominal GDP growth

Sheet Income Statement
B2: INCOME STATEMENT – Aon plc (USD $mm)
C3: FY2023A | D3: FY2024A | E3: FY2025A | F3: FY2026E | G3: FY2027E | H3: FY2028E | I3: FY2029E | J3: FY2030E
B4: Revenue | C4: 13376 | D4: 15698 | E4: 17111 | F4: =E4*(1+Assumptions!$C$7) -> 18052.105 | G4: =F4*(1+Assumptions!$C$8) -> 18990.814 | H4: =G4*(1+Assumptions!$C$9) -> 19940.355 | I4: =H4*(1+Assumptions!$C$10) -> 20897.492 | J4: =I4*(1+Assumptions!$C$11) -> 21837.879
B5: EBITDA | C5: 4011 | D5: 4934 | E5: 5546 | F5: =F4*Assumptions!$C$17 -> 5957.1947 | G5: =G4*Assumptions!$C$17 -> 6266.9688 | H5: =H4*Assumptions!$C$17 -> 6580.3172 | I5: =I4*Assumptions!$C$17 -> 6896.1724 | J5: =J4*Assumptions!$C$17 -> 7206.5002
B6: D&A | C6: 366 | D6: 440 | E6: 480 | F6: =F4*Assumptions!$C$18 -> 505.45894 | G6: =G4*Assumptions!$C$18 -> 531.7428 | H6: =H4*Assumptions!$C$18 -> 558.32995 | I6: =I4*Assumptions!$C$18 -> 585.12978 | J6: =J4*Assumptions!$C$18 -> 611.46062
B7: EBIT | C7: 3645 | D7: 4494 | E7: 5066 | F7: =F5-F6 -> 5451.7357 | G7: =G5-G6 -> 5735.226 | H7: =H5-H6 -> 6021.9873 | I7: =I5-I6 -> 6311.0427 | J7: =J5-J6 -> 6595.0396
B8: Interest Expense | C8: 520 | D8: 608 | E8: 720 | F8: =E8*1.02 -> 734.4 | G8: =F8*1.02 -> 749.088 | H8: =G8*1.02 -> 764.06976 | I8: =H8*1.02 -> 779.35116 | J8: =I8*1.02 -> 794.93818
B9: EBT | C9: 3125 | D9: 3886 | E9: 4346 | F9: =F7-F8 -> 4717.3357 | G9: =G7-G8 -> 4986.138 | H9: =H7-H8 -> 5257.9175 | I9: =I7-I8 -> 5531.6915 | J9: =J7-J8 -> 5800.1014
B10: Tax | C10: 590 | D10: 718 | E10: 826 | F10: =F9*Assumptions!$C$31 -> 896.29378 | G10: =G9*Assumptions!$C$31 -> 947.36621 | H10: =H9*Assumptions!$C$31 -> 999.00433 | I10: =I9*Assumptions!$C$31 -> 1051.0214 | J10: =J9*Assumptions!$C$31 -> 1102.0193
B11: Net Income | C11: 2535 | D11: 3168 | E11: 3520 | F11: =F9-F10 -> 3821.0419 | G11: =G9-G10 -> 4038.7718 | H11: =H9-H10 -> 4258.9132 | I11: =I9-I10 -> 4480.6701 | J11: =J9-J10 -> 4698.0821
B13: EBITDA Margin % | C13: =C5/C4 -> 0.29986543 | D13: =D5/D4 -> 0.31430756 | E13: =E5/E4 -> 0.32411899 | F13: =F5/F4 -> 0.33 | G13: =G5/G4 -> 0.33 | H13: =H5/H4 -> 0.33 | I13: =I5/I4 -> 0.33 | J13: =J5/J4 -> 0.33
B14: Revenue Growth % | D14: =(D4-C4)/C4 -> 0.1735945 | E14: =(E4-D4)/D4 -> 0.090011466 | F14: =(F4-E4)/E4 -> 0.055 | G14: =(G4-F4)/F4 -> 0.052 | H14: =(H4-G4)/G4 -> 0.05 | I14: =(I4-H4)/H4 -> 0.048 | J14: =(J4-I4)/I4 -> 0.045

Sheet FCF Build
B2: FREE CASH FLOW BUILD – Aon plc (USD $mm)
C3: FY2026E | D3: FY2027E | E3: FY2028E | F3: FY2029E | G3: FY2030E
B4: EBIT | C4: ='Income Statement'!F7 -> 5451.7357 | D4: ='Income Statement'!G7 -> 5735.226 | E4: ='Income Statement'!H7 -> 6021.9873 | F4: ='Income Statement'!I7 -> 6311.0427 | G4: ='Income Statement'!J7 -> 6595.0396
B5: Less: Taxes on EBIT | C5: =-'Income Statement'!F7*Assumptions!$C$31 -> -1035.8298 | D5: =-'Income Statement'!G7*Assumptions!$C$31 -> -1089.6929 | E5: =-'Income Statement'!H7*Assumptions!$C$31 -> -1144.1776 | F5: =-'Income Statement'!I7*Assumptions!$C$31 -> -1199.0981 | G5: =-'Income Statement'!J7*Assumptions!$C$31 -> -1253.0575
B6: NOPAT (Net Operating Profit after Tax) | C6: =C4+C5 -> 4415.9059 | D6: =D4+D5 -> 4645.533 | E6: =E4+E5 -> 4877.8097 | F6: =F4+F5 -> 5111.9445 | G6: =G4+G5 -> 5341.9821
B7: Add: D&A | C7: ='Income Statement'!F6 -> 505.45894 | D7: ='Income Statement'!G6 -> 531.7428 | E7: ='Income Statement'!H6 -> 558.32995 | F7: ='Income Statement'!I6 -> 585.12978 | G7: ='Income Statement'!J6 -> 611.46062
B8: Less: Capex | C8: =-'Income Statement'!F4*Assumptions!$C$19 -> -324.93789 | D8: =-'Income Statement'!G4*Assumptions!$C$19 -> -341.83466 | E8: =-'Income Statement'!H4*Assumptions!$C$19 -> -358.92639 | F8: =-'Income Statement'!I4*Assumptions!$C$19 -> -376.15486 | G8: =-'Income Statement'!J4*Assumptions!$C$19 -> -393.08183
B9: Less: Change in Working Capital | C9: ='Income Statement'!F4*Assumptions!$C$20 -> -90.260525 | D9: ='Income Statement'!G4*Assumptions!$C$20 -> -94.954072 | E9: ='Income Statement'!H4*Assumptions!$C$20 -> -99.701776 | F9: ='Income Statement'!I4*Assumptions!$C$20 -> -104.48746 | G9: ='Income Statement'!J4*Assumptions!$C$20 -> -109.1894
B10: Unlevered Free Cash Flow | C10: =C6+C7+C8+C9 -> 4506.1665 | D10: =D6+D7+D8+D9 -> 4740.4871 | E10: =E6+E7+E8+E9 -> 4977.5115 | F10: =F6+F7+F8+F9 -> 5216.432 | G10: =G6+G7+G8+G9 -> 5451.1715

Sheet DCF Valuation
B2: DCF VALUATION – Aon plc (USD $mm)
B4: Key Value Drivers
B5: WACC | C5: =Assumptions!C35 -> 0.0784706
B6: Terminal Growth Rate | C6: =Assumptions!C36 -> 0.025
B8: Discount Factors & PV of FCFs
C9: FY2026E | D9: FY2027E | E9: FY2028E | F9: FY2029E | G9: FY2030E | H9: Total
B10: Period (n) | C10: 1 | D10: 2 | E10: 3 | F10: 4 | G10: 5
B11: Discount Factor 1/(1+WACC)^n | C11: =1/(1+$C$5)^C10 -> 0.927239 | D11: =1/(1+$C$5)^D10 -> 0.85977216 | E11: =1/(1+$C$5)^E10 -> 0.79721428 | F11: =1/(1+$C$5)^F10 -> 0.73920817 | G11: =1/(1+$C$5)^G10 -> 0.68542264
B12: Unlevered FCF ($mm) | C12: ='FCF Build'!C10 -> 4506.1665 | D12: ='FCF Build'!D10 -> 4740.4871 | E12: ='FCF Build'!E10 -> 4977.5115 | F12: ='FCF Build'!F10 -> 5216.432 | G12: ='FCF Build'!G10 -> 5451.1715
B13: PV of FCF ($mm) | C13: =C11*C12 -> 4178.2933 | D13: =D11*D12 -> 4075.7388 | E13: =E11*E12 -> 3968.1432 | F13: =F11*F12 -> 3856.0292 | G13: =G11*G12 -> 3736.3564 | H13: =SUM(C13:G13) -> 19814.561
B15: Terminal Value (Gordon Growth Model)
B16: Terminal Year FCF (FY2029E, $mm) | C16: ='FCF Build'!G10 -> 5451.1715
B17: Terminal Value = FCF x (1+g) / (WACC – g) | C17: =C16*(1+C6)/(C5-C6) -> 104495.76
B18: PV of Terminal Value | C18: =C17/(1+C5)^5 -> 71623.757
B20: Enterprise & Equity Value Bridge
B21: PV of FCFs ($mm) | C21: =H13 -> 19814.561
B22: PV of Terminal Value ($mm) | C22: =C18 -> 71623.757
B23: Enterprise Value ($mm) | C23: =C21+C22 -> 91438.318
B24: Less: Net Debt ($mm) | C24: 8200 | D24: Source: Aon 2025 10-K (total debt $15.2bn less cash)
B25: Less: Minority Interests ($mm) | C25: 0
B26: Equity Value ($mm) | C26: =C23-C24-C25 -> 83238.318
B27: Shares Outstanding (mm) | C27: 214
B28: Implied Share Price (USD) | C28: =C26/C27 -> 388.9641
B29: Current Share Price (USD, approx.) | C29: 322
B30: Implied Upside / (Downside) | C30: =(C28-C29)/C29 -> 0.20796305

Sheet Sensitivity
B2: SENSITIVITY ANALYSIS – Implied Share Price (USD) | WACC vs Terminal Growth Rate
B3: TGR \ WACC → | C3: 0.08 | D3: 0.085 | E3: 0.09 | F3: 0.095 | G3: 0.1 | H3: 0.105 | I3: 0.11 | J3: 0.115 | K3: 0.12
B4: 0.015 | C4: =(('FCF Build'!$C$10/(1+C$3)^1+'FCF Build'!$D$10/(1+C$3)^2+'FCF Build'!$E$10/(1+C$3)^3+'FCF Build'!$F$10/(1+C$3)^4+'FCF Build'!$G$10/(1+C$3)^5+('FCF Build'!$G$10*(1+$B4)/(C$3-$B4))/(1+C$3)^5)-'DCF Valuation'!$C$24-'DCF Valuation'!$C$25)/'DCF Valuation'!$C$27 -> 324.60185 | D4: =(('FCF Build'!$C$10/(1+D$3)^1+'FCF Build'!$D$10/(1+D$3)^2+'FCF Build'!$E$10/(1+D$3)^3+'FCF Build'!$F$10/(1+D$3)^4+'FCF Build'!$G$10/(1+D$3)^5+('FCF Build'!$G$10*(1+$B4)/(D$3-$B4))/(1+D$3)^5)-'DCF Valuation'!$C$24-'DCF Valuation'!$C$25)/'DCF Valuation'!$C$27 -> 298.28386 | E4: =(('FCF Build'!$C$10/(1+E$3)^1+'FCF Build'!$D$10/(1+E$3)^2+'FCF Build'!$E$10/(1+E$3)^3+'FCF Build'!$F$10/(1+E$3)^4+'FCF Build'!$G$10/(1+E$3)^5+('FCF Build'!$G$10*(1+$B4)/(E$3-$B4))/(1+E$3)^5)-'DCF Valuation'!$C$24-'DCF Valuation'!$C$25)/'DCF Valuation'!$C$27 -> 275.48149 | F4: =(('FCF Build'!$C$10/(1+F$3)^1+'FCF Build'!$D$10/(1+F$3)^2+'FCF Build'!$E$10/(1+F$3)^3+'FCF Build'!$F$10/(1+F$3)^4+'FCF Build'!$G$10/(1+F$3)^5+('FCF Build'!$G$10*(1+$B4)/(F$3-$B4))/(1+F$3)^5)-'DCF Valuation'!$C$24-'DCF Valuation'!$C$25)/'DCF Valuation'!$C$27 -> 255.53542 | G4: =(('FCF Build'!$C$10/(1+G$3)^1+'FCF Build'!$D$10/(1+G$3)^2+'FCF Build'!$E$10/(1+G$3)^3+'FCF Build'!$F$10/(1+G$3)^4+'FCF Build'!$G$10/(1+G$3)^5+('FCF Build'!$G$10*(1+$B4)/(G$3-$B4))/(1+G$3)^5)-'DCF Valuation'!$C$24-'DCF Valuation'!$C$25)/'DCF Valuation'!$C$27 -> 237.94146 | H4: =(('FCF Build'!$C$10/(1+H$3)^1+'FCF Build'!$D$10/(1+H$3)^2+'FCF Build'!$E$10/(1+H$3)^3+'FCF Build'!$F$10/(1+H$3)^4+'FCF Build'!$G$10/(1+H$3)^5+('FCF Build'!$G$10*(1+$B4)/(H$3-$B4))/(1+H$3)^5)-'DCF Valuation'!$C$24-'DCF Valuation'!$C$25)/'DCF Valuation'!$C$27 -> 222.30748 | I4: =(('FCF Build'!$C$10/(1+I$3)^1+'FCF Build'!$D$10/(1+I$3)^2+'FCF Build'!$E$10/(1+I$3)^3+'FCF Build'!$F$10/(1+I$3)^4+'FCF Build'!$G$10/(1+I$3)^5+('FCF Build'!$G$10*(1+$B4)/(I$3-$B4))/(1+I$3)^5)-'DCF Valuation'!$C$24-'DCF Valuation'!$C$25)/'DCF Valuation'!$C$27 -> 208.32389 | J4: =(('FCF Build'!$C$10/(1+J$3)^1+'FCF Build'!$D$10/(1+J$3)^2+'FCF Build'!$E$10/(1+J$3)^3+'FCF Build'!$F$10/(1+J$3)^4+'FCF Build'!$G$10/(1+J$3)^5+('FCF Build'!$G$10*(1+$B4)/(J$3-$B4))/(1+J$3)^5)-'DCF Valuation'!$C$24-'DCF Valuation'!$C$25)/'DCF Valuation'!$C$27 -> 195.74303 | K4: =(('FCF Build'!$C$10/(1+K$3)^1+'FCF Build'!$D$10/(1+K$3)^2+'FCF Build'!$E$10/(1+K$3)^3+'FCF Build'!$F$10/(1+K$3)^4+'FCF Build'!$G$10/(1+K$3)^5+('FCF Build'!$G$10*(1+$B4)/(K$3-$B4))/(1+K$3)^5)-'DCF Valuation'!$C$24-'DCF Valuation'!$C$25)/'DCF Valuation'!$C$27 -> 184.36442
B5: 0.02 | C5: =(('FCF Build'!$C$10/(1+C$3)^1+'FCF Build'!$D$10/(1+C$3)^2+'FCF Build'!$E$10/(1+C$3)^3+'FCF Build'!$F$10/(1+C$3)^4+'FCF Build'!$G$10/(1+C$3)^5+('FCF Build'!$G$10*(1+$B5)/(C$3-$B5))/(1+C$3)^5)-'DCF Valuation'!$C$24-'DCF Valuation'!$C$25)/'DCF Valuation'!$C$27 -> 348.606 | D5: =(('FCF Build'!$C$10/(1+D$3)^1+'FCF Build'!$D$10/(1+D$3)^2+'FCF Build'!$E$10/(1+D$3)^3+'FCF Build'!$F$10/(1+D$3)^4+'FCF Build'!$G$10/(1+D$3)^5+('FCF Build'!$G$10*(1+$B5)/(D$3-$B5))/(1+D$3)^5)-'DCF Valuation'!$C$24-'DCF Valuation'!$C$25)/'DCF Valuation'!$C$27 -> 318.4822 | E5: =(('FCF Build'!$C$10/(1+E$3)^1+'FCF Build'!$D$10/(1+E$3)^2+'FCF Build'!$E$10/(1+E$3)^3+'FCF Build'!$F$10/(1+E$3)^4+'FCF Build'!$G$10/(1+E$3)^5+('FCF Build'!$G$10*(1+$B5)/(E$3-$B5))/(1+E$3)^5)-'DCF Valuation'!$C$24-'DCF Valuation'!$C$25)/'DCF Valuation'!$C$27 -> 292.66773 | F5: =(('FCF Build'!$C$10/(1+F$3)^1+'FCF Build'!$D$10/(1+F$3)^2+'FCF Build'!$E$10/(1+F$3)^3+'FCF Build'!$F$10/(1+F$3)^4+'FCF Build'!$G$10/(1+F$3)^5+('FCF Build'!$G$10*(1+$B5)/(F$3-$B5))/(1+F$3)^5)-'DCF Valuation'!$C$24-'DCF Valuation'!$C$25)/'DCF Valuation'!$C$27 -> 270.30059 | G5: =(('FCF Build'!$C$10/(1+G$3)^1+'FCF Build'!$D$10/(1+G$3)^2+'FCF Build'!$E$10/(1+G$3)^3+'FCF Build'!$F$10/(1+G$3)^4+'FCF Build'!$G$10/(1+G$3)^5+('FCF Build'!$G$10*(1+$B5)/(G$3-$B5))/(1+G$3)^5)-'DCF Valuation'!$C$24-'DCF Valuation'!$C$25)/'DCF Valuation'!$C$27 -> 250.73429 | H5: =(('FCF Build'!$C$10/(1+H$3)^1+'FCF Build'!$D$10/(1+H$3)^2+'FCF Build'!$E$10/(1+H$3)^3+'FCF Build'!$F$10/(1+H$3)^4+'FCF Build'!$G$10/(1+H$3)^5+('FCF Build'!$G$10*(1+$B5)/(H$3-$B5))/(1+H$3)^5)-'DCF Valuation'!$C$24-'DCF Valuation'!$C$25)/'DCF Valuation'!$C$27 -> 233.47445 | I5: =(('FCF Build'!$C$10/(1+I$3)^1+'FCF Build'!$D$10/(1+I$3)^2+'FCF Build'!$E$10/(1+I$3)^3+'FCF Build'!$F$10/(1+I$3)^4+'FCF Build'!$G$10/(1+I$3)^5+('FCF Build'!$G$10*(1+$B5)/(I$3-$B5))/(1+I$3)^5)-'DCF Valuation'!$C$24-'DCF Valuation'!$C$25)/'DCF Valuation'!$C$27 -> 218.13658 | J5: =(('FCF Build'!$C$10/(1+J$3)^1+'FCF Build'!$D$10/(1+J$3)^2+'FCF Build'!$E$10/(1+J$3)^3+'FCF Build'!$F$10/(1+J$3)^4+'FCF Build'!$G$10/(1+J$3)^5+('FCF Build'!$G$10*(1+$B5)/(J$3-$B5))/(1+J$3)^5)-'DCF Valuation'!$C$24-'DCF Valuation'!$C$25)/'DCF Valuation'!$C$27 -> 204.4171 | K5: =(('FCF Build'!$C$10/(1+K$3)^1+'FCF Build'!$D$10/(1+K$3)^2+'FCF Build'!$E$10/(1+K$3)^3+'FCF Build'!$F$10/(1+K$3)^4+'FCF Build'!$G$10/(1+K$3)^5+('FCF Build'!$G$10*(1+$B5)/(K$3-$B5))/(1+K$3)^5)-'DCF Valuation'!$C$24-'DCF Valuation'!$C$25)/'DCF Valuation'!$C$27 -> 192.07318
B6: 0.025 | C6: =(('FCF Build'!$C$10/(1+C$3)^1+'FCF Build'!$D$10/(1+C$3)^2+'FCF Build'!$E$10/(1+C$3)^3+'FCF Build'!$F$10/(1+C$3)^4+'FCF Build'!$G$10/(1+C$3)^5+('FCF Build'!$G$10*(1+$B6)/(C$3-$B6))/(1+C$3)^5)-'DCF Valuation'!$C$24-'DCF Valuation'!$C$25)/'DCF Valuation'!$C$27 -> 376.97455 | D6: =(('FCF Build'!$C$10/(1+D$3)^1+'FCF Build'!$D$10/(1+D$3)^2+'FCF Build'!$E$10/(1+D$3)^3+'FCF Build'!$F$10/(1+D$3)^4+'FCF Build'!$G$10/(1+D$3)^5+('FCF Build'!$G$10*(1+$B6)/(D$3-$B6))/(1+D$3)^5)-'DCF Valuation'!$C$24-'DCF Valuation'!$C$25)/'DCF Valuation'!$C$27 -> 342.04693 | E6: =(('FCF Build'!$C$10/(1+E$3)^1+'FCF Build'!$D$10/(1+E$3)^2+'FCF Build'!$E$10/(1+E$3)^3+'FCF Build'!$F$10/(1+E$3)^4+'FCF Build'!$G$10/(1+E$3)^5+('FCF Build'!$G$10*(1+$B6)/(E$3-$B6))/(1+E$3)^5)-'DCF Valuation'!$C$24-'DCF Valuation'!$C$25)/'DCF Valuation'!$C$27 -> 312.498 | F6: =(('FCF Build'!$C$10/(1+F$3)^1+'FCF Build'!$D$10/(1+F$3)^2+'FCF Build'!$E$10/(1+F$3)^3+'FCF Build'!$F$10/(1+F$3)^4+'FCF Build'!$G$10/(1+F$3)^5+('FCF Build'!$G$10*(1+$B6)/(F$3-$B6))/(1+F$3)^5)-'DCF Valuation'!$C$24-'DCF Valuation'!$C$25)/'DCF Valuation'!$C$27 -> 287.17506 | G6: =(('FCF Build'!$C$10/(1+G$3)^1+'FCF Build'!$D$10/(1+G$3)^2+'FCF Build'!$E$10/(1+G$3)^3+'FCF Build'!$F$10/(1+G$3)^4+'FCF Build'!$G$10/(1+G$3)^5+('FCF Build'!$G$10*(1+$B6)/(G$3-$B6))/(1+G$3)^5)-'DCF Valuation'!$C$24-'DCF Valuation'!$C$25)/'DCF Valuation'!$C$27 -> 265.23282 | H6: =(('FCF Build'!$C$10/(1+H$3)^1+'FCF Build'!$D$10/(1+H$3)^2+'FCF Build'!$E$10/(1+H$3)^3+'FCF Build'!$F$10/(1+H$3)^4+'FCF Build'!$G$10/(1+H$3)^5+('FCF Build'!$G$10*(1+$B6)/(H$3-$B6))/(1+H$3)^5)-'DCF Valuation'!$C$24-'DCF Valuation'!$C$25)/'DCF Valuation'!$C$27 -> 246.0373 | I6: =(('FCF Build'!$C$10/(1+I$3)^1+'FCF Build'!$D$10/(1+I$3)^2+'FCF Build'!$E$10/(1+I$3)^3+'FCF Build'!$F$10/(1+I$3)^4+'FCF Build'!$G$10/(1+I$3)^5+('FCF Build'!$G$10*(1+$B6)/(I$3-$B6))/(1+I$3)^5)-'DCF Valuation'!$C$24-'DCF Valuation'!$C$25)/'DCF Valuation'!$C$27 -> 229.1037 | J6: =(('FCF Build'!$C$10/(1+J$3)^1+'FCF Build'!$D$10/(1+J$3)^2+'FCF Build'!$E$10/(1+J$3)^3+'FCF Build'!$F$10/(1+J$3)^4+'FCF Build'!$G$10/(1+J$3)^5+('FCF Build'!$G$10*(1+$B6)/(J$3-$B6))/(1+J$3)^5)-'DCF Valuation'!$C$24-'DCF Valuation'!$C$25)/'DCF Valuation'!$C$27 -> 214.05496 | K6: =(('FCF Build'!$C$10/(1+K$3)^1+'FCF Build'!$D$10/(1+K$3)^2+'FCF Build'!$E$10/(1+K$3)^3+'FCF Build'!$F$10/(1+K$3)^4+'FCF Build'!$G$10/(1+K$3)^5+('FCF Build'!$G$10*(1+$B6)/(K$3-$B6))/(1+K$3)^5)-'DCF Valuation'!$C$24-'DCF Valuation'!$C$25)/'DCF Valuation'!$C$27 -> 200.5934
B7: 0.03 | C7: =(('FCF Build'!$C$10/(1+C$3)^1+'FCF Build'!$D$10/(1+C$3)^2+'FCF Build'!$E$10/(1+C$3)^3+'FCF Build'!$F$10/(1+C$3)^4+'FCF Build'!$G$10/(1+C$3)^5+('FCF Build'!$G$10*(1+$B7)/(C$3-$B7))/(1+C$3)^5)-'DCF Valuation'!$C$24-'DCF Valuation'!$C$25)/'DCF Valuation'!$C$27 -> 411.01681 | D7: =(('FCF Build'!$C$10/(1+D$3)^1+'FCF Build'!$D$10/(1+D$3)^2+'FCF Build'!$E$10/(1+D$3)^3+'FCF Build'!$F$10/(1+D$3)^4+'FCF Build'!$G$10/(1+D$3)^5+('FCF Build'!$G$10*(1+$B7)/(D$3-$B7))/(1+D$3)^5)-'DCF Valuation'!$C$24-'DCF Valuation'!$C$25)/'DCF Valuation'!$C$27 -> 369.89616 | E7: =(('FCF Build'!$C$10/(1+E$3)^1+'FCF Build'!$D$10/(1+E$3)^2+'FCF Build'!$E$10/(1+E$3)^3+'FCF Build'!$F$10/(1+E$3)^4+'FCF Build'!$G$10/(1+E$3)^5+('FCF Build'!$G$10*(1+$B7)/(E$3-$B7))/(1+E$3)^5)-'DCF Valuation'!$C$24-'DCF Valuation'!$C$25)/'DCF Valuation'!$C$27 -> 335.63332 | F7: =(('FCF Build'!$C$10/(1+F$3)^1+'FCF Build'!$D$10/(1+F$3)^2+'FCF Build'!$E$10/(1+F$3)^3+'FCF Build'!$F$10/(1+F$3)^4+'FCF Build'!$G$10/(1+F$3)^5+('FCF Build'!$G$10*(1+$B7)/(F$3-$B7))/(1+F$3)^5)-'DCF Valuation'!$C$24-'DCF Valuation'!$C$25)/'DCF Valuation'!$C$27 -> 306.64561 | G7: =(('FCF Build'!$C$10/(1+G$3)^1+'FCF Build'!$D$10/(1+G$3)^2+'FCF Build'!$E$10/(1+G$3)^3+'FCF Build'!$F$10/(1+G$3)^4+'FCF Build'!$G$10/(1+G$3)^5+('FCF Build'!$G$10*(1+$B7)/(G$3-$B7))/(1+G$3)^5)-'DCF Valuation'!$C$24-'DCF Valuation'!$C$25)/'DCF Valuation'!$C$27 -> 281.80257 | H7: =(('FCF Build'!$C$10/(1+H$3)^1+'FCF Build'!$D$10/(1+H$3)^2+'FCF Build'!$E$10/(1+H$3)^3+'FCF Build'!$F$10/(1+H$3)^4+'FCF Build'!$G$10/(1+H$3)^5+('FCF Build'!$G$10*(1+$B7)/(H$3-$B7))/(1+H$3)^5)-'DCF Valuation'!$C$24-'DCF Valuation'!$C$25)/'DCF Valuation'!$C$27 -> 260.27519 | I7: =(('FCF Build'!$C$10/(1+I$3)^1+'FCF Build'!$D$10/(1+I$3)^2+'FCF Build'!$E$10/(1+I$3)^3+'FCF Build'!$F$10/(1+I$3)^4+'FCF Build'!$G$10/(1+I$3)^5+('FCF Build'!$G$10*(1+$B7)/(I$3-$B7))/(1+I$3)^5)-'DCF Valuation'!$C$24-'DCF Valuation'!$C$25)/'DCF Valuation'!$C$27 -> 241.44172 | J7: =(('FCF Build'!$C$10/(1+J$3)^1+'FCF Build'!$D$10/(1+J$3)^2+'FCF Build'!$E$10/(1+J$3)^3+'FCF Build'!$F$10/(1+J$3)^4+'FCF Build'!$G$10/(1+J$3)^5+('FCF Build'!$G$10*(1+$B7)/(J$3-$B7))/(1+J$3)^5)-'DCF Valuation'!$C$24-'DCF Valuation'!$C$25)/'DCF Valuation'!$C$27 -> 224.82668 | K7: =(('FCF Build'!$C$10/(1+K$3)^1+'FCF Build'!$D$10/(1+K$3)^2+'FCF Build'!$E$10/(1+K$3)^3+'FCF Build'!$F$10/(1+K$3)^4+'FCF Build'!$G$10/(1+K$3)^5+('FCF Build'!$G$10*(1+$B7)/(K$3-$B7))/(1+K$3)^5)-'DCF Valuation'!$C$24-'DCF Valuation'!$C$25)/'DCF Valuation'!$C$27 -> 210.0603
B8: 0.035 | C8: =(('FCF Build'!$C$10/(1+C$3)^1+'FCF Build'!$D$10/(1+C$3)^2+'FCF Build'!$E$10/(1+C$3)^3+'FCF Build'!$F$10/(1+C$3)^4+'FCF Build'!$G$10/(1+C$3)^5+('FCF Build'!$G$10*(1+$B8)/(C$3-$B8))/(1+C$3)^5)-'DCF Valuation'!$C$24-'DCF Valuation'!$C$25)/'DCF Valuation'!$C$27 -> 452.62401 | D8: =(('FCF Build'!$C$10/(1+D$3)^1+'FCF Build'!$D$10/(1+D$3)^2+'FCF Build'!$E$10/(1+D$3)^3+'FCF Build'!$F$10/(1+D$3)^4+'FCF Build'!$G$10/(1+D$3)^5+('FCF Build'!$G$10*(1+$B8)/(D$3-$B8))/(1+D$3)^5)-'DCF Valuation'!$C$24-'DCF Valuation'!$C$25)/'DCF Valuation'!$C$27 -> 403.31524 | E8: =(('FCF Build'!$C$10/(1+E$3)^1+'FCF Build'!$D$10/(1+E$3)^2+'FCF Build'!$E$10/(1+E$3)^3+'FCF Build'!$F$10/(1+E$3)^4+'FCF Build'!$G$10/(1+E$3)^5+('FCF Build'!$G$10*(1+$B8)/(E$3-$B8))/(1+E$3)^5)-'DCF Valuation'!$C$24-'DCF Valuation'!$C$25)/'DCF Valuation'!$C$27 -> 362.97506 | F8: =(('FCF Build'!$C$10/(1+F$3)^1+'FCF Build'!$D$10/(1+F$3)^2+'FCF Build'!$E$10/(1+F$3)^3+'FCF Build'!$F$10/(1+F$3)^4+'FCF Build'!$G$10/(1+F$3)^5+('FCF Build'!$G$10*(1+$B8)/(F$3-$B8))/(1+F$3)^5)-'DCF Valuation'!$C$24-'DCF Valuation'!$C$25)/'DCF Valuation'!$C$27 -> 329.36125 | G8: =(('FCF Build'!$C$10/(1+G$3)^1+'FCF Build'!$D$10/(1+G$3)^2+'FCF Build'!$E$10/(1+G$3)^3+'FCF Build'!$F$10/(1+G$3)^4+'FCF Build'!$G$10/(1+G$3)^5+('FCF Build'!$G$10*(1+$B8)/(G$3-$B8))/(1+G$3)^5)-'DCF Valuation'!$C$24-'DCF Valuation'!$C$25)/'DCF Valuation'!$C$27 -> 300.92152 | H8: =(('FCF Build'!$C$10/(1+H$3)^1+'FCF Build'!$D$10/(1+H$3)^2+'FCF Build'!$E$10/(1+H$3)^3+'FCF Build'!$F$10/(1+H$3)^4+'FCF Build'!$G$10/(1+H$3)^5+('FCF Build'!$G$10*(1+$B8)/(H$3-$B8))/(1+H$3)^5)-'DCF Valuation'!$C$24-'DCF Valuation'!$C$25)/'DCF Valuation'!$C$27 -> 276.54707 | I8: =(('FCF Build'!$C$10/(1+I$3)^1+'FCF Build'!$D$10/(1+I$3)^2+'FCF Build'!$E$10/(1+I$3)^3+'FCF Build'!$F$10/(1+I$3)^4+'FCF Build'!$G$10/(1+I$3)^5+('FCF Build'!$G$10*(1+$B8)/(I$3-$B8))/(1+I$3)^5)-'DCF Valuation'!$C$24-'DCF Valuation'!$C$25)/'DCF Valuation'!$C$27 -> 255.4248 | J8: =(('FCF Build'!$C$10/(1+J$3)^1+'FCF Build'!$D$10/(1+J$3)^2+'FCF Build'!$E$10/(1+J$3)^3+'FCF Build'!$F$10/(1+J$3)^4+'FCF Build'!$G$10/(1+J$3)^5+('FCF Build'!$G$10*(1+$B8)/(J$3-$B8))/(1+J$3)^5)-'DCF Valuation'!$C$24-'DCF Valuation'!$C$25)/'DCF Valuation'!$C$27 -> 236.94487 | K8: =(('FCF Build'!$C$10/(1+K$3)^1+'FCF Build'!$D$10/(1+K$3)^2+'FCF Build'!$E$10/(1+K$3)^3+'FCF Build'!$F$10/(1+K$3)^4+'FCF Build'!$G$10/(1+K$3)^5+('FCF Build'!$G$10*(1+$B8)/(K$3-$B8))/(1+K$3)^5)-'DCF Valuation'!$C$24-'DCF Valuation'!$C$25)/'DCF Valuation'!$C$27 -> 220.64095
B9: Yellow = Base Case (WACC 9.0%, TGR 2.5%) | Current price: ~$322 | June 2026

Sheet Trading Comps
B2: TRADING COMPARABLES – Aon plc | Professional Services / Insurance Advisory Peers
C3: Market Data (USD $mm) | F3: EV / EBITDA | I3: P / E
B4: Company | C4: Mkt Cap | D4: Net Debt | E4: EV | F4: CY2025A | G4: CY2026E | H4: CY2027E | I4: CY2025A | J4: CY2026E | K4: CY2027E
B5: Marsh & McLennan (MMC) | C5: 88000 | D5: 5800 | E5: =C5+D5 -> 93800 | F5: 18.5 | G5: 17.2 | H5: 16 | I5: 27.5 | J5: 25.2 | K5: 23.1
B6: Willis Towers Watson (WTW) | C6: 30500 | D6: 4500 | E6: =C6+D6 -> 35000 | F6: 13 | G6: 12.2 | H6: 11.5 | I6: 19.8 | J6: 18.2 | K6: 16.8
B7: Arthur J. Gallagher (AJG) | C7: 58000 | D7: 8800 | E7: =C7+D7 -> 66800 | F7: 17 | G7: 15.8 | H7: 14.7 | I7: 32.5 | J7: 29.8 | K7: 27.2
B8: Howden Group (Private) | C8: 12500 | D8: 2300 | E8: =C8+D8 -> 14800 | F8: 14.8 | G8: 13.6 | H8: 12.6 | I8: 22.5 | J8: 20.5 | K8: 18.8
B9: Lockton (Private) | C9: 10000 | D9: 900 | E9: =C9+D9 -> 10900 | F9: 12.5 | G9: 11.6 | H9: 10.8 | I9: 19 | J9: 17.5 | K9: 16.2
B10: Aon plc (AON) ◀ Subject | C10: 68900 | D10: 8200 | E10: =C10+D10 -> 77100 | F10: 16.2 | G10: 15.1 | H10: 14.1 | I10: 24.8 | J10: 22.6 | K10: 20.8
B12: Peer Summary Statistics
B13: Statistic | C13: — | D13: — | E13: — | F13: EV/EBITDA 24A | G13: EV/EBITDA 25E | H13: EV/EBITDA 26E | I13: P/E 24A | J13: P/E 25E | K13: P/E 26E
B14: Mean | F14: =AVERAGE(F5:F9) -> 15.16 | G14: =AVERAGE(G5:G9) -> 14.08 | H14: =AVERAGE(H5:H9) -> 13.12 | I14: =AVERAGE(I5:I9) -> 24.26 | J14: =AVERAGE(J5:J9) -> 22.24 | K14: =AVERAGE(K5:K9) -> 20.42
B15: Median | F15: =MEDIAN(F5:F9) -> 14.8 | G15: =MEDIAN(G5:G9) -> 13.6 | H15: =MEDIAN(H5:H9) -> 12.6 | I15: =MEDIAN(I5:I9) -> 22.5 | J15: =MEDIAN(J5:J9) -> 20.5 | K15: =MEDIAN(K5:K9) -> 18.8
B16: Min | F16: =MIN(F5:F9) -> 12.5 | G16: =MIN(G5:G9) -> 11.6 | H16: =MIN(H5:H9) -> 10.8 | I16: =MIN(I5:I9) -> 19 | J16: =MIN(J5:J9) -> 17.5 | K16: =MIN(K5:K9) -> 16.2
B17: Max | F17: =MAX(F5:F9) -> 18.5 | G17: =MAX(G5:G9) -> 17.2 | H17: =MAX(H5:H9) -> 16 | I17: =MAX(I5:I9) -> 32.5 | J17: =MAX(J5:J9) -> 29.8 | K17: =MAX(K5:K9) -> 27.2
B18: 25th Pct | F18: =PERCENTILE(F5:F9,0.25) -> 13 | G18: =PERCENTILE(G5:G9,0.25) -> 12.2 | H18: =PERCENTILE(H5:H9,0.25) -> 11.5 | I18: =PERCENTILE(I5:I9,0.25) -> 19.8 | J18: =PERCENTILE(J5:J9,0.25) -> 18.2 | K18: =PERCENTILE(K5:K9,0.25) -> 16.8
B19: 75th Pct | F19: =PERCENTILE(F5:F9,0.75) -> 17 | G19: =PERCENTILE(G5:G9,0.75) -> 15.8 | H19: =PERCENTILE(H5:H9,0.75) -> 14.7 | I19: =PERCENTILE(I5:I9,0.75) -> 27.5 | J19: =PERCENTILE(J5:J9,0.75) -> 25.2 | K19: =PERCENTILE(K5:K9,0.75) -> 23.1
B22: Implied Share Price from Comps (using Aon FY2025E EBITDA & Net Income)
B23: Method | C23: Multiple Used | D23: Aon Metric ($mm) | E23: Implied EV / Equity ($mm) | F23: Less: Net Debt | G23: Implied Equity ($mm) | H23: Shares (mm) | I23: Implied Price (USD)
B24: EV/EBITDA – Mean | C24: =F14 -> 15.16 | D24: ='Income Statement'!E5 -> 5546 | E24: =C24*D24 -> 84077.36 | F24: ='DCF Valuation'!C24 -> 8200 | G24: =E24-F24 -> 75877.36 | H24: ='DCF Valuation'!C27 -> 214 | I24: =G24/H24 -> 354.5671
B25: EV/EBITDA – Median | C25: =F15 -> 14.8 | D25: ='Income Statement'!E5 -> 5546 | E25: =C25*D25 -> 82080.8 | F25: ='DCF Valuation'!C24 -> 8200 | G25: =E25-F25 -> 73880.8 | H25: ='DCF Valuation'!C27 -> 214 | I25: =G25/H25 -> 345.23738
B26: P/E – Mean | C26: =I14 -> 24.26 | D26: ='Income Statement'!E11 -> 3520 | E26: N/A – equity method | F26: — | G26: =C26*D26 -> 85395.2 | H26: ='DCF Valuation'!C27 -> 214 | I26: =G26/H26 -> 399.04299
B27: P/E – Median | C27: =I15 -> 22.5 | D27: ='Income Statement'!E11 -> 3520 | E27: N/A – equity method | F27: — | G27: =C27*D27 -> 79200 | H27: ='DCF Valuation'!C27 -> 214 | I27: =G27/H27 -> 370.09346
B29: Source: Bloomberg / FactSet consensus estimates (June 2026). Private company multiples (Howden, Lockton) from industry reports. All figures approximate; for illustrative purposes.

Sheet Football Field
B2: FOOTBALL FIELD – Aon plc Implied Share Price (USD) | Valuation Summary | I2: Label | J2: Low | K2: Bar Width | L2: Mid
B3: Methodology | C3: Low | D3: Mid / Base | E3: High | F3: Current Price | I3: =B4 -> DCF – Base Case | J3: =C4 -> 388.9641 | K3: =E4-C4 -> 0 | L3: =D4 -> 388.9641
B4: DCF – Base Case | C4: ='DCF Valuation'!C28 -> 388.9641 | D4: ='DCF Valuation'!C28 -> 388.9641 | E4: ='DCF Valuation'!C28 -> 388.9641 | F4: ='DCF Valuation'!C29 -> 322 | I4: =B5 -> DCF – Sensitivity Range | J4: =C5 -> 184.36442 | K4: =E5-C5 -> 268.25959 | L4: =D5 -> 388.9641
B5: DCF – Sensitivity Range | C5: =Sensitivity!K4 -> 184.36442 | D5: ='DCF Valuation'!C28 -> 388.9641 | E5: =Sensitivity!C8 -> 452.62401 | F5: ='DCF Valuation'!C29 -> 322 | I5: =B6 -> EV/EBITDA Comps | J5: =C6 -> 345.23738 | K5: =E6-C6 -> 9.3297196 | L5: =D6 -> 349.90224
B6: EV/EBITDA Comps | C6: =MIN('Trading Comps'!I24,'Trading Comps'!I25) -> 345.23738 | D6: =AVERAGE('Trading Comps'!I24,'Trading Comps'!I25) -> 349.90224 | E6: =MAX('Trading Comps'!I24,'Trading Comps'!I25) -> 354.5671 | F6: ='DCF Valuation'!C29 -> 322 | I6: =B7 -> P/E Comps | J6: =C7 -> 370.09346 | K6: =E7-C7 -> 28.949533 | L6: =D7 -> 384.56822
B7: P/E Comps | C7: =MIN('Trading Comps'!I26,'Trading Comps'!I27) -> 370.09346 | D7: =AVERAGE('Trading Comps'!I26,'Trading Comps'!I27) -> 384.56822 | E7: =MAX('Trading Comps'!I26,'Trading Comps'!I27) -> 399.04299 | F7: ='DCF Valuation'!C29 -> 322 | I7: =B8 -> 52-Week Trading Range | J7: =C8 -> 305 | K7: =E8-C8 -> 76 | L7: =D8 -> 343
B8: 52-Week Trading Range | C8: 305 | D8: 343 | E8: 381 | F8: ='DCF Valuation'!C29 -> 322
